kaag_pdf/__init__.py
kaag_pdf/colors.py
kaag_pdf/components.py
kaag_pdf/fonts.py
kaag_pdf/generator.py
kaag_pdf/styles.py
kaag_pdf/assets/fonts/ivy-presto-display.ttf
kaag_pdf/assets/fonts/obviously-bold.ttf
kaag_pdf/assets/fonts/poppins-regular.ttf
kaag_pdf_exports-0.3.0.dist-info/licenses/LICENSE
kaag_pdf_exports-0.3.0.dist-info/METADATA
kaag_pdf_exports-0.3.0.dist-info/WHEEL
kaag_pdf_exports-0.3.0.dist-info/top_level.txt
kaag_pdf_exports-0.3.0.dist-info/RECORD
